simple_manga_downloader/SMD.py
simple_manga_downloader/__init__.py
simple_manga_downloader/arg_parser.py
simple_manga_downloader/config_parser.py
simple_manga_downloader/utils.py
simple_manga_downloader/modules/__init__.py
simple_manga_downloader/modules/manga.py
simple_manga_downloader/modules/mangadex_org.py
simple_manga_downloader/modules/mangakakalot_com.py
simple_manga_downloader/modules/manganato_com.py
simple_manga_downloader/modules/mangatown_com.py
simple_manga_downloader-1.16.1.dist-info/LICENSE
simple_manga_downloader-1.16.1.dist-info/METADATA
simple_manga_downloader-1.16.1.dist-info/WHEEL
simple_manga_downloader-1.16.1.dist-info/entry_points.txt
simple_manga_downloader-1.16.1.dist-info/top_level.txt
simple_manga_downloader-1.16.1.dist-info/RECORD
