Metadata-Version: 2.1
Name: simple-manga-downloader
Version: 1.16.1
Summary: Simple manga console downloader
Home-page: https://github.com/Kanjirito/simple-manga-downloader
Author: Kanjirito
Author-email: kanjirito@protonmail.com
License: GPLv3
Project-URL: Bug Tracker, https://github.com/Kanjirito/simple-manga-downloader/issues
Project-URL: Use Guide, https://github.com/Kanjirito/simple-manga-downloader/blob/master/USAGE.md
Project-URL: Changelog, https://github.com/Kanjirito/simple-manga-downloader/blob/master/CHANGELOG.md
Keywords: manga,downloader
Platform: UNKNOWN
Classifier: Programming Language :: Python :: 3
Classifier: License :: OSI Approved :: GNU General Public License v3 (GPLv3)
Classifier: Environment :: Console
Requires-Python: >=3.6
License-File: LICENSE
Requires-Dist: requests (~=2.23)
Requires-Dist: beautifulsoup4 (~=4.9)
Requires-Dist: urllib3 (>=1.26.5)
